taclextra/__init__.py
taclextra/jitc.py
taclextra/lifetime.py
taclextra/paired_intersector.py
taclextra/paternity.py
taclextra/sole_exception.py
taclextra/sole_exceptions.py
taclextra/assets/jitc/chord.js
taclextra/assets/jitc/grouped_bar.js
taclextra/assets/jitc/matrix.js
taclextra/assets/jitc/report.css
taclextra/assets/jitc/stacked_bar.js
taclextra/assets/templates/jitc.html
taclextra/assets/templates/sole_exception.html
taclextra/cli/__init__.py
taclextra/cli/int_all.py
taclextra/cli/jitc.py
taclextra/cli/lifetime.py
taclextra/cli/paternity.py
taclextra/cli/sole_exception.py
taclextra/cli/sole_exceptions.py
tacl_extra-1.2.0.dist-info/LICENSE
tacl_extra-1.2.0.dist-info/METADATA
tacl_extra-1.2.0.dist-info/WHEEL
tacl_extra-1.2.0.dist-info/entry_points.txt
tacl_extra-1.2.0.dist-info/top_level.txt
tacl_extra-1.2.0.dist-info/RECORD
