Metadata-Version: 2.1
Name: tacl-extra
Version: 1.2.0
Summary: Collection of scripts to generate various TACL results and reports
Author-email: Jamie Norrish <jamie@artefact.org.nz>
License: GNU GENERAL PUBLIC LICENSE
Project-URL: homepage, https://github.com/ajenhl/tacl-extra
Project-URL: documentation, http://tacl-extra.readthedocs.io/en/latest/
Classifier: Environment :: Console
Classifier: License :: OSI Approved :: GNU General Public License v3 or later (GPLv3+)
Classifier: Programming Language :: Python :: 3
Classifier: Topic :: Text Processing :: Linguistic
Requires-Python: >=3.8
License-File: LICENSE
Requires-Dist: tacl >=5.3.0
